ripe.atlas.cousteau-2.2.0-py3.11-nspkg.pth
ripe/atlas/cousteau/__init__.py
ripe/atlas/cousteau/api_listing.py
ripe/atlas/cousteau/api_meta_data.py
ripe/atlas/cousteau/exceptions.py
ripe/atlas/cousteau/measurement.py
ripe/atlas/cousteau/measurement_tagging.py
ripe/atlas/cousteau/request.py
ripe/atlas/cousteau/source.py
ripe/atlas/cousteau/stream.py
ripe/atlas/cousteau/version.py
ripe_atlas_cousteau-2.2.0.dist-info/licenses/LICENSE
ripe_atlas_cousteau-2.2.0.dist-info/METADATA
ripe_atlas_cousteau-2.2.0.dist-info/WHEEL
ripe_atlas_cousteau-2.2.0.dist-info/namespace_packages.txt
ripe_atlas_cousteau-2.2.0.dist-info/top_level.txt
ripe_atlas_cousteau-2.2.0.dist-info/RECORD
