Metadata-Version: 2.4
Name: ripe.atlas.cousteau
Version: 2.2.0
Summary: Python wrapper for RIPE Atlas API
Home-page: https://github.com/RIPE-NCC/ripe-atlas-cousteau
Author: The RIPE Atlas Team
Author-email: atlas@ripe.net
Maintainer: The RIPE Atlas Team
Maintainer-email: atlas@ripe.net
License: GPLv3
Keywords: RIPE,RIPE NCC,RIPE Atlas
Classifier: Operating System :: POSIX
Classifier: Operating System :: Unix
Classifier: Programming Language :: Python
Classifier: Programming Language :: Python :: 3.10
Classifier: Programming Language :: Python :: 3.11
Classifier: Programming Language :: Python :: 3.12
Classifier: Programming Language :: Python :: 3.13
Classifier: Topic :: Internet :: WWW/HTTP
Classifier: Topic :: Software Development :: Libraries :: Python Modules
License-File: LICENSE
Requires-Dist: python-dateutil
Requires-Dist: requests~=2.32.0
Requires-Dist: websocket-client~=1.9.0
Requires-Dist: typing-extensions
Dynamic: author
Dynamic: author-email
Dynamic: classifier
Dynamic: description
Dynamic: home-page
Dynamic: keywords
Dynamic: license
Dynamic: license-file
Dynamic: maintainer
Dynamic: maintainer-email
Dynamic: requires-dist
Dynamic: summary
